{
  "params": {
    "sigma_pyr_deg": 15.0,
    "sigma_som_deg": 15.0,
    "n_nodes": 64,
    "amplitude": 0.5,
    "condition": "WT"
  },
  "steady_state": {
    "baseline_pyr_hz": 72.109,
    "peak_pyr_cue_hz": 121.656,
    "delay_pyr_center_hz": 73.079,
    "delay_pyr_opposite_hz": 71.268
  },
  "bump_metrics": {
    "center_mean_deg": 14.0312,
    "center_std_deg": 119.2035,
    "amplitude_mean": 0.0071,
    "width_mean_deg": 54.4856,
    "drift_rate_deg_per_s": 353.3985,
    "diffusion_deg2_per_s": 337627.5685,
    "error_from_cue_deg": 165.9688
  }
}