{
  "params": {
    "sigma_pyr_deg": 15.0,
    "sigma_som_deg": 15.0,
    "n_nodes": 128,
    "amplitude": 0.5,
    "condition": "WT"
  },
  "steady_state": {
    "baseline_pyr_hz": 0.047,
    "peak_pyr_cue_hz": 10.41,
    "delay_pyr_center_hz": 0.035,
    "delay_pyr_opposite_hz": 0.018
  },
  "bump_metrics": {
    "center_mean_deg": 224.6518,
    "center_std_deg": 127.5129,
    "amplitude_mean": 0.1236,
    "width_mean_deg": 54.0454,
    "drift_rate_deg_per_s": -201.8035,
    "diffusion_deg2_per_s": 287725.0998,
    "error_from_cue_deg": 44.6518
  }
}