{
  "params": {
    "sigma_pyr_deg": 15.0,
    "sigma_som_deg": 15.0,
    "n_nodes": 64,
    "amplitude": 0.8,
    "condition": "WT"
  },
  "steady_state": {
    "baseline_pyr_hz": 52.428,
    "peak_pyr_cue_hz": 200.0,
    "delay_pyr_center_hz": 58.342,
    "delay_pyr_opposite_hz": 48.666
  },
  "bump_metrics": {
    "center_mean_deg": 275.8995,
    "center_std_deg": 110.3459,
    "amplitude_mean": 0.0429,
    "width_mean_deg": 54.002,
    "drift_rate_deg_per_s": -172.1616,
    "diffusion_deg2_per_s": 204647.5719,
    "error_from_cue_deg": 95.8995
  }
}