{
  "params": {
    "sigma_pyr_deg": 15.0,
    "sigma_som_deg": 15.0,
    "n_nodes": 64,
    "amplitude": 0.6,
    "condition": "WT"
  },
  "steady_state": {
    "baseline_pyr_hz": 51.272,
    "peak_pyr_cue_hz": 158.404,
    "delay_pyr_center_hz": 54.376,
    "delay_pyr_opposite_hz": 48.398
  },
  "bump_metrics": {
    "center_mean_deg": 289.6925,
    "center_std_deg": 140.342,
    "amplitude_mean": 0.0385,
    "width_mean_deg": 54.8813,
    "drift_rate_deg_per_s": -42.9501,
    "diffusion_deg2_per_s": 196368.9611,
    "error_from_cue_deg": 109.6925
  }
}