{
  "params": {
    "w_pyr_pyr_inter": 0.002514,
    "w_pv_global": 0.03,
    "sigma_pyr_deg": 15.0,
    "n_nodes": 128,
    "amplitude": 0.55,
    "condition": "WT"
  },
  "steady_state": {
    "baseline_pyr_hz": 10.373,
    "peak_pyr_cue_hz": 200.0,
    "delay_pyr_center_hz": 77.464,
    "delay_pyr_opposite_hz": 0.0
  },
  "bump_metrics": {
    "center_mean_deg": 181.1247,
    "center_std_deg": 73.0051,
    "amplitude_mean": 0.6611,
    "width_mean_deg": 24.8773,
    "drift_rate_deg_per_s": 40.2011,
    "diffusion_deg2_per_s": 48523.7435,
    "error_from_cue_deg": 1.1247
  },
  "post_transient": {
    "post_mean_pyr_hz": 0.0,
    "post_var_pyr_hz": 0.0,
    "post_frac_above_30hz": 0.0,
    "post_frac_above_50hz": 0.0,
    "post_state": "SILENT"
  }
}