{
  "params": {
    "w_pyr_pyr_inter": 0.002,
    "w_pv_global": 0.07,
    "sigma_pyr_deg": 30.0,
    "n_nodes": 128,
    "amplitude": 0.6,
    "condition": "WT"
  },
  "steady_state": {
    "baseline_pyr_hz": 0.172,
    "peak_pyr_cue_hz": 2.596,
    "delay_pyr_center_hz": 0.004,
    "delay_pyr_opposite_hz": 0.0
  },
  "turing_gain_delay": {
    "bump_node": 0.0002,
    "mean_background": 0.0
  },
  "bump_metrics": {
    "center_mean_deg": 136.9026,
    "center_std_deg": 133.5602,
    "amplitude_mean": 0.6601,
    "width_mean_deg": 33.7926,
    "drift_rate_deg_per_s": 111.0241,
    "diffusion_deg2_per_s": 109374.4056,
    "error_from_cue_deg": 43.0974
  }
}