{
  "params": {
    "sigma_pyr_deg": 15.0,
    "sigma_som_deg": 15.0,
    "n_nodes": 128,
    "amplitude": 0.7,
    "condition": "WT"
  },
  "steady_state": {
    "baseline_pyr_hz": 1.784,
    "peak_pyr_cue_hz": 170.372,
    "delay_pyr_center_hz": 49.597,
    "delay_pyr_opposite_hz": 1.623
  },
  "bump_metrics": {
    "center_mean_deg": 179.9999,
    "center_std_deg": 0.2263,
    "amplitude_mean": 0.7942,
    "width_mean_deg": 30.4778,
    "drift_rate_deg_per_s": 0.0341,
    "diffusion_deg2_per_s": 0.4689,
    "error_from_cue_deg": 0.0001
  }
}